whalevad/__init__.py
whalevad/__version__.py
whalevad/model.py
whalevad/spectrogram.py
whalevad/utils.py
whalevad/weights.py
whalevad-0.1.5.dist-info/licenses/LICENSE
whalevad-0.1.5.dist-info/WHEEL
whalevad-0.1.5.dist-info/METADATA
whalevad-0.1.5.dist-info/RECORD
