Metadata-Version: 2.4
Name: whalevad
Version: 0.1.5
Summary: A lightweight sound event detection system for discovering Baleen whale calls in marine audio recordings
Author: Christiaan M. Geldenhuys, Günther Tonitz
Author-email: Christiaan M. Geldenhuys <cmgeldenhuys@sun.ac.za>, Günther Tonitz <gtonitz@sun.ac.za>
License-Expression: GPL-3.0-or-later
License-File: LICENSE
Classifier: Development Status :: 3 - Alpha
Classifier: Intended Audience :: Developers
Classifier: Intended Audience :: Science/Research
Classifier: License :: OSI Approved :: GNU General Public License v3 (GPLv3)
Classifier: Operating System :: OS Independent
Classifier: Programming Language :: Python :: 3
Classifier: Programming Language :: Python :: 3.11
Classifier: Programming Language :: Python :: 3.12
Classifier: Topic :: Scientific/Engineering :: Artificial Intelligence
Classifier: Topic :: Software Development :: Libraries :: Python Modules
Classifier: Topic :: Multimedia :: Sound/Audio :: Analysis
Requires-Dist: torch>=2.0.0
Requires-Dist: torchaudio>=2.0.0
Requires-Dist: numpy>=1.24.0
Requires-Dist: pytest>=7.0.0 ; extra == 'dev'
Requires-Dist: black>=23.0.0 ; extra == 'dev'
Requires-Dist: ruff ; extra == 'dev'
Requires-Dist: remotezip ; extra == 'examples'
Requires-Python: >=3.11
Project-URL: Homepage, https://github.com/CMGeldenhuys/Whale-VAD
Project-URL: Issues, https://github.com/CMGeldenhuys/Whale-VAD/issues
Provides-Extra: dev
Provides-Extra: examples
